rhaptos.cnxmlutils-2.10.0-py2.7-nspkg.pth
rhaptos/cnxmlutils/__init__.py
rhaptos/cnxmlutils/_version.py
rhaptos/cnxmlutils/addsectiontags.py
rhaptos/cnxmlutils/aloha2html.py
rhaptos/cnxmlutils/html2cnxml.py
rhaptos/cnxmlutils/html2validcnxml.py
rhaptos/cnxmlutils/odt2cnxml.py
rhaptos/cnxmlutils/symbols.py
rhaptos/cnxmlutils/utils.py
rhaptos/cnxmlutils/validatecnxml.py
rhaptos/cnxmlutils/xml2xhtml.py
rhaptos/cnxmlutils/schema/cnxml/rng/0.6/cnxml.rng
rhaptos/cnxmlutils/schema/cnxml/rng/0.7/bibtexml-1.0.rng
rhaptos/cnxmlutils/schema/cnxml/rng/0.7/cnxml-abstract-defs.rng
rhaptos/cnxmlutils/schema/cnxml/rng/0.7/cnxml-abstract-driver.rng
rhaptos/cnxmlutils/schema/cnxml/rng/0.7/cnxml-common.rng
rhaptos/cnxmlutils/schema/cnxml/rng/0.7/cnxml-defs.rng
rhaptos/cnxmlutils/schema/cnxml/rng/0.7/cnxml-fragment-jing.rng
rhaptos/cnxmlutils/schema/cnxml/rng/0.7/cnxml-simplified.rng
rhaptos/cnxmlutils/schema/cnxml/rng/0.7/cnxml.rng
rhaptos/cnxmlutils/schema/cnxml/rng/0.7/mathml2.rng
rhaptos/cnxmlutils/schema/cnxml/rng/0.7/mdml-defs-0.5.rng
rhaptos/cnxmlutils/schema/cnxml/rng/0.7/qml-defs-1.0.rng
rhaptos/cnxmlutils/tests/__init__.py
rhaptos/cnxmlutils/tests/test_xsl_cnxml_to_html5.py
rhaptos/cnxmlutils/tests/test_xsl_html5_to_cnxml.py
rhaptos/cnxmlutils/xsl/__init__.py
rhaptos/cnxmlutils/xsl/aloha-to-html5-pass01-leveled-headers.xsl
rhaptos/cnxmlutils/xsl/aloha-to-html5-pass02-new-min-header-level.xsl
rhaptos/cnxmlutils/xsl/aloha-to-html5-pass03-nested-headers.xsl
rhaptos/cnxmlutils/xsl/aloha-to-html5-pass04-headers2sections.xsl
rhaptos/cnxmlutils/xsl/aloha-to-html5-pass05-mathjax2mathml.xsl
rhaptos/cnxmlutils/xsl/aloha-to-html5-pass06-postprocessing.xsl
rhaptos/cnxmlutils/xsl/cnxml-to-html5-metadata.xsl
rhaptos/cnxmlutils/xsl/cnxml-to-html5.xsl
rhaptos/cnxmlutils/xsl/collxml-to-html5.xsl
rhaptos/cnxmlutils/xsl/generateIds.xsl
rhaptos/cnxmlutils/xsl/html5-indent.xsl
rhaptos/cnxmlutils/xsl/html5-to-aloha.xsl
rhaptos/cnxmlutils/xsl/html5-to-cnxml-pass01-cleanup.xsl
rhaptos.cnxmlutils-2.10.0.dist-info/LICENSE.txt
rhaptos.cnxmlutils-2.10.0.dist-info/METADATA
rhaptos.cnxmlutils-2.10.0.dist-info/WHEEL
rhaptos.cnxmlutils-2.10.0.dist-info/namespace_packages.txt
rhaptos.cnxmlutils-2.10.0.dist-info/top_level.txt
rhaptos.cnxmlutils-2.10.0.dist-info/RECORD
