Metadata-Version: 2.1
Name: rhaptos.cnxmlutils
Version: 2.10.0
Summary: UNKNOWN
Home-page: https://github.com/Connexions/rhaptos.cnxmlutils
Author: OpenStax/Connexions Developers
Author-email: info@cnx.org
License: GPL
Platform: UNKNOWN
Classifier: Programming Language :: Python
Requires-Dist: setuptools
Requires-Dist: lxml
